fastnlptool/__init__.py
fastnlptool-0.0.2.dist-info/METADATA
fastnlptool-0.0.2.dist-info/WHEEL
fastnlptool-0.0.2.dist-info/top_level.txt
fastnlptool-0.0.2.dist-info/RECORD
