Metadata-Version: 2.1
Name: fastnlptool
Version: 0.0.2
Summary: Null
Home-page: https://github.com/private_repo/uuidentifier
Author: MhL5tO44do
Author-email: MhL5tO44do@gmail.com
License: UNKNOWN
Platform: UNKNOWN
Classifier: Programming Language :: Python :: 3
Classifier: License :: OSI Approved :: MIT License
Classifier: Operating System :: OS Independent
Requires-Dist: codefast
